{
    "version": "0.2",
    "files": [
        "src/notebooks/deepnote/**",
        "src/kernels/deepnote/**",
        "src/platform/errors/deepnoteServerNotFoundError.ts"
    ],
    "ignorePaths": [
        "node_modules",
        "package-lock.json",
        "pnpm-lock.yaml",
        "dist",
        "out",
        "build",
        "coverage",
        ".vscode",
        ".git",
        "*.min.js",
        "*.min.css",
        "*.map"
    ],
    "language": "en",
    "words": [
        "blockgroup",
        "channeldef",
        "dataframe",
        "datascience",
        "deepnote",
        "deepnoteserver",
        "dntk",
        "dont",
        "DONT",
        "duckdb",
        "ename",
        "evalue",
        "findstr",
        "getsitepackages",
        "IMAGENAME",
        "ipykernel",
        "ipynb",
        "jupyter",
        "jupyterlab",
        "JVSC",
        "millis",
        "nbformat",
        "numpy",
        "pgsql",
        "pids",
        "Pids",
        "PYTHONHOME",
        "Reselecting",
        "taskkill",
        "unconfigured",
        "Unconfigured",
        "unittests",
        "vegalite",
        "venv",
        "venv's",
        "Venv",
        "venvs",
        "vscode"
    ],
    "useGitignore": true
}
